getmyqr/__init__.py
getmyqr/cli.py
getmyqr/generator.py
getmyqr-1.0.dist-info/METADATA
getmyqr-1.0.dist-info/WHEEL
getmyqr-1.0.dist-info/entry_points.txt
getmyqr-1.0.dist-info/top_level.txt
getmyqr-1.0.dist-info/RECORD
