Metadata-Version: 2.1
Name: getmyqr
Version: 1.0
Summary: A simple QR code generator using a free API
Home-page: https://https://mrfidal.in/py/getmyqr
Author: MrFidal
Author-email: mrfidal@proton.me
Classifier: Programming Language :: Python :: 3
Classifier: License :: OSI Approved :: MIT License
Classifier: Operating System :: OS Independent
Requires-Python: >=3.6
Requires-Dist: requests
